mtunnel/__init__.py
mtunnel-0.0.0.data/data/etc/mtunnel.yml.example
mtunnel-0.0.0.dist-info/AUTHORS
mtunnel-0.0.0.dist-info/LICENSE
mtunnel-0.0.0.dist-info/METADATA
mtunnel-0.0.0.dist-info/WHEEL
mtunnel-0.0.0.dist-info/entry_points.txt
mtunnel-0.0.0.dist-info/pbr.json
mtunnel-0.0.0.dist-info/top_level.txt
mtunnel-0.0.0.dist-info/RECORD
