Metadata-Version: 2.1
Name: mtunnel
Version: 0.0.0
Summary: Creates multiple background SSH tunnels for services within a project and stage.
Home-page: https://github.com/datashaman/mtunnel
Author: Marlin Forbes
Author-email: marlinf@datashaman.com
License: MIT
Keywords: ssh,ssh-tunnel
Classifier: Development Status :: 4 - Beta
Classifier: Environment :: Console
Classifier: Intended Audience :: Developers
Classifier: License :: OSI Approved :: MIT License
Classifier: Operating System :: OS Independent
Classifier: Programming Language :: Python
License-File: LICENSE
License-File: AUTHORS
Requires-Dist: bgtunnel
Requires-Dist: botocore
Requires-Dist: click
Requires-Dist: python-dotenv
Requires-Dist: pyyaml
Requires-Dist: requests
